LICENSE.txt
MANIFEST.in
README.md
pyinvoke.py
setup.py
pyinvoke.egg-info/PKG-INFO
pyinvoke.egg-info/SOURCES.txt
pyinvoke.egg-info/dependency_links.txt
pyinvoke.egg-info/top_level.txt