Metadata-Version: 2.1
Name: pyinvoke
Version: 1.0.3
Summary: UNKNOWN
Home-page: https://github.com/NiklasRosenstein/pyinvoke
Author: Niklas Rosenstein
Author-email: rosensteinniklas@gmail.com
License: MIT
Platform: UNKNOWN
